django_cron_tasks/__init__.py
django_cron_tasks/admin.py
django_cron_tasks/apps.py
django_cron_tasks/lock.py
django_cron_tasks/models.py
django_cron_tasks/runner.py
django_cron_tasks/management/__init__.py
django_cron_tasks/management/commands/__init__.py
django_cron_tasks/management/commands/run_cron_tasks.py
django_cron_tasks/migrations/0001_initial.py
django_cron_tasks/migrations/0002_lock.py
django_cron_tasks/migrations/0003_manually_started_tasks.py
django_cron_tasks/migrations/0004_upgrade_indexes.py
django_cron_tasks/migrations/__init__.py
django_cron_tasks-1.2.1.dist-info/licenses/LICENSE
django_cron_tasks-1.2.1.dist-info/METADATA
django_cron_tasks-1.2.1.dist-info/WHEEL
django_cron_tasks-1.2.1.dist-info/top_level.txt
django_cron_tasks-1.2.1.dist-info/RECORD
