Metadata-Version: 2.4
Name: django_cron_tasks
Version: 1.2.1
Summary: Django background tasks, ran via crontab.
Home-page: https://github.com/henu/django_cron_tasks
Author: Henrik Heino
Author-email: henrik.heino@gmail.com
License: MIT License
License-File: LICENSE
Dynamic: author
Dynamic: author-email
Dynamic: home-page
Dynamic: license
Dynamic: license-file
Dynamic: summary
